gitdo/__init__.py
gitdo/cli.py
gitdo/markdown_parser.py
gitdo/models.py
gitdo/storage.py
gitdo-0.2.4.dist-info/METADATA
gitdo-0.2.4.dist-info/WHEEL
gitdo-0.2.4.dist-info/entry_points.txt
gitdo-0.2.4.dist-info/licenses/LICENSE
gitdo-0.2.4.dist-info/RECORD
