Metadata-Version: 2.4
Name: gitdo
Version: 0.2.4
Summary: Simple CLI tool to plan your work
Project-URL: Homepage, https://github.com/s0b0lev/gitdo
Project-URL: Repository, https://github.com/s0b0lev/gitdo
Author-email: Your Name <your.email@example.com>
License-File: LICENSE
Keywords: cli,git,planning,productivity,task
Classifier: Development Status :: 3 - Alpha
Classifier: Intended Audience :: Developers
Classifier: License :: OSI Approved :: MIT License
Classifier: Programming Language :: Python :: 3
Classifier: Programming Language :: Python :: 3.12
Classifier: Programming Language :: Python :: 3.13
Requires-Python: >=3.12
Requires-Dist: click>=8.1.7
Requires-Dist: rich>=13.7.0
Provides-Extra: dev
Requires-Dist: pytest-cov>=4.1.0; extra == 'dev'
Requires-Dist: pytest>=8.0.0; extra == 'dev'
Requires-Dist: ruff>=0.1.0; extra == 'dev'
